devops_ai/__init__.py
devops_ai/cli.py
devops_ai/core.py
devops_ai/dashboard.py
devops_ai/dashboard_original.py
devops_ai/agents/__init__.py
devops_ai/agents/analyze_logs.py
devops_ai/agents/base_agent.py
devops_ai/agents/code_quality.py
devops_ai/agents/contributors.py
devops_ai/agents/dependency_check.py
devops_ai/agents/docker_generation.py
devops_ai/agents/infra_suggest.py
devops_ai/agents/optimize.py
devops_ai/agents/repo_analyze.py
devops_ai/agents/security_scan.py
devops_ai/ui/__init__.py
devops_ai/ui/panels.py
devops_ai/ui/tool_handlers.py
syntera_ai-0.1.3.dist-info/licenses/LICENSE
syntera_ai-0.1.3.dist-info/METADATA
syntera_ai-0.1.3.dist-info/WHEEL
syntera_ai-0.1.3.dist-info/entry_points.txt
syntera_ai-0.1.3.dist-info/top_level.txt
syntera_ai-0.1.3.dist-info/RECORD
